filenum
