Metadata-Version: 2.1
Name: filenum
Version: 0.0.2
Summary: file number in directory
Home-page: UNKNOWN
Author: Chen chuan
Author-email: chenc224@163.com
License: UNKNOWN
Platform: UNKNOWN
Classifier: Programming Language :: Python :: 2
Classifier: Programming Language :: Python :: 3
Classifier: License :: OSI Approved :: MIT License
Classifier: Operating System :: OS Independent
